pykalt/__init__.py
pykalt/kalt.py
pykalt-1.5.dist-info/METADATA
pykalt-1.5.dist-info/WHEEL
pykalt-1.5.dist-info/entry_points.txt
pykalt-1.5.dist-info/licenses/LICENSE
pykalt-1.5.dist-info/RECORD
