Metadata-Version: 2.4
Name: pykalt
Version: 1.5
Summary: KALT is a Kubernetes Audit Logs Toolkit. It alows analyzing Kubernetes audit.log files.
Project-URL: Homepage, https://github.com/FlorentFlament/kalt
Project-URL: Issues, https://github.com/FlorentFlament/kalt/issues
Author-email: Florent Flament <contact@florentflament.com>
License-File: LICENSE
Keywords: Kubernetes,audit,audit.log,k8s,log
Classifier: License :: OSI Approved :: GNU General Public License v3 (GPLv3)
Classifier: Operating System :: POSIX :: Linux
Classifier: Programming Language :: Python :: 3
Requires-Python: >=3
Requires-Dist: click
Requires-Dist: tabulate
